sentinel_rs/__init__.py
sentinel_rs/sentinel_rs.cpython-310-x86_64-linux-gnu.so
sentinel_rs-0.1.1.dist-info/METADATA
sentinel_rs-0.1.1.dist-info/WHEEL
sentinel_rs-0.1.1.dist-info/licenses/LICENSE
sentinel_rs-0.1.1.dist-info/RECORD
