Metadata-Version: 2.4
Name: sentinel-rs
Version: 0.1.1
Classifier: Development Status :: 4 - Beta
Classifier: Intended Audience :: Developers
Classifier: License :: OSI Approved :: MIT License
Classifier: Programming Language :: Python :: 3
Classifier: Programming Language :: Python :: 3.8
Classifier: Programming Language :: Python :: 3.9
Classifier: Programming Language :: Python :: 3.10
Classifier: Programming Language :: Python :: 3.11
Classifier: Programming Language :: Python :: 3.12
Classifier: Programming Language :: Rust
Classifier: Programming Language :: Python :: Implementation :: CPython
Classifier: Programming Language :: Python :: Implementation :: PyPy
Classifier: Topic :: Software Development :: Libraries :: Python Modules
Classifier: Topic :: Text Processing
Classifier: Topic :: System :: Logging
Requires-Dist: pytest ; extra == 'tests'
Requires-Dist: pytest-benchmark ; extra == 'tests'
Provides-Extra: tests
License-File: LICENSE
Summary: High-performance pattern matching engine for Python, powered by Rust
Keywords: rust,regex,pattern-matching,log-processing,anonymization,performance
Author-email: Harsh Raj <saketharshraj@gmail.com>
License: MIT
Requires-Python: >=3.8
Project-URL: Documentation, https://github.com/saketharshraj/sentinel-rs#readme
Project-URL: Homepage, https://github.com/saketharshraj/sentinel-rs
Project-URL: Issues, https://github.com/saketharshraj/sentinel-rs/issues
Project-URL: Repository, https://github.com/saketharshraj/sentinel-rs
